pyvpn
setup.py
cisco_vpn.egg-info/PKG-INFO
cisco_vpn.egg-info/SOURCES.txt
cisco_vpn.egg-info/dependency_links.txt
cisco_vpn.egg-info/requires.txt
cisco_vpn.egg-info/top_level.txt
lib/__init__.py
lib/connect.py