Metadata-Version: 1.0
Name: cisco_vpn
Version: 0.0.14
Summary: Connect Cisco VPN With Python
Home-page: https://github.com/phodal/vpnc
Author: Phodal Huang
Author-email: h@phodal.com
License: MIT License
Keywords: cisco,vpn,cisco vpn
Platform: any
